styly_netsync/__init__.py
styly_netsync/__main__.py
styly_netsync/adapters.py
styly_netsync/binary_serializer.py
styly_netsync/cli.py
styly_netsync/client.py
styly_netsync/client_simulator.py
styly_netsync/events.py
styly_netsync/network_utils.py
styly_netsync/nv_sync.py
styly_netsync/rest_bridge.py
styly_netsync/server.py
styly_netsync/types.py
styly_netsync_server-0.6.1.dist-info/licenses/LICENSE
styly_netsync_server-0.6.1.dist-info/METADATA
styly_netsync_server-0.6.1.dist-info/WHEEL
styly_netsync_server-0.6.1.dist-info/entry_points.txt
styly_netsync_server-0.6.1.dist-info/top_level.txt
styly_netsync_server-0.6.1.dist-info/RECORD
