Metadata-Version: 2.4
Name: styly-netsync-server
Version: 0.6.1
Summary: STYLY NetSync Server - Multiplayer framework for Location-Based Entertainment VR/MR experiences
Author-email: "STYLY, Inc." <info@styly.inc>
License: Apache-2.0
Project-URL: Homepage, https://styly.inc
Project-URL: Repository, https://github.com/styly-dev/STYLY-NetSync
Project-URL: Documentation, https://github.com/styly-dev/STYLY-NetSync/blob/main/README.md
Project-URL: Issues, https://github.com/styly-dev/STYLY-NetSync/issues
Keywords: unity,multiplayer,vr,mr,location-based-entertainment,real-time,zeromq,networking
Classifier: Development Status :: 4 - Beta
Classifier: Intended Audience :: Developers
Classifier: License :: OSI Approved :: Apache Software License
Classifier: Operating System :: OS Independent
Classifier: Programming Language :: Python :: 3
Classifier: Programming Language :: Python :: 3.11
Classifier: Programming Language :: Python :: 3.12
Classifier: Topic :: Games/Entertainment
Classifier: Topic :: Internet
Classifier: Topic :: Software Development :: Libraries :: Python Modules
Classifier: Topic :: System :: Networking
Requires-Python: >=3.11
License-File: LICENSE
Requires-Dist: pyzmq>=26.0.0
Requires-Dist: fastapi>=0.115.0
Requires-Dist: uvicorn[standard]>=0.30.0
Requires-Dist: msgpack>=1.0.5
Requires-Dist: psutil>=5.9.0
Provides-Extra: dev
Requires-Dist: pytest>=7.0.0; extra == "dev"
Requires-Dist: pytest-cov>=4.0.0; extra == "dev"
Requires-Dist: black>=23.0.0; extra == "dev"
Requires-Dist: ruff>=0.1.0; extra == "dev"
Requires-Dist: mypy>=1.0.0; extra == "dev"
Dynamic: license-file
